setup.py
git_tags.egg-info/PKG-INFO
git_tags.egg-info/SOURCES.txt
git_tags.egg-info/dependency_links.txt
git_tags.egg-info/entry_points.txt
git_tags.egg-info/requires.txt
git_tags.egg-info/top_level.txt
tags/__init__.py
tags/git.py
tags/lookup.py
tags/release.py
tags/utils.py
tags/cli/__init__.py
tags/cli/lookup.py
tags/cli/main.py
tags/cli/messages.py
tags/cli/notes.py
tags/cli/printing.py
tags/cli/release.py