Metadata-Version: 1.0
Name: git-tags
Version: 0.2.1
Summary: CLI for managing release tags in a Git repository
Home-page: https://github.com/bmcorser/git-tags-py
Author: bmcorser
Author-email: bmcorser@gmail.com
License: UNKNOWN
Platform: UNKNOWN
